CHANGES.txt
LICENSE
MANIFEST.in
README.rst
setup.py
mlserve/__init__.py
mlserve/__main__.py
mlserve/async_client.py
mlserve/consts.py
mlserve/exceptions.py
mlserve/handlers.py
mlserve/loaders.py
mlserve/main.py
mlserve/middleware.py
mlserve/mypy_types.py
mlserve/schema_builder.py
mlserve/server_utils.py
mlserve/stats.py
mlserve/utils.py
mlserve/worker.py
mlserve.egg-info/PKG-INFO
mlserve.egg-info/SOURCES.txt
mlserve.egg-info/dependency_links.txt
mlserve.egg-info/entry_points.txt
mlserve.egg-info/requires.txt
mlserve.egg-info/top_level.txt
mlserve.egg-info/zip-safe
mlserve/static/.gitkeep
mlserve/static/App.757cce9c.js
mlserve/static/App.9042ff4d.css
mlserve/static/App.b7bb14de.map
mlserve/static/index.html