Metadata-Version: 1.1
Name: mlserve
Version: 0.0.1a6
Summary: mlserve -- turns python model into RESTful API with automatically generated UI.
Home-page: https://github.com/jettify/mlserve
Author: Nikolay Novik
Author-email: nickolainovik@gmail.com
License: Apache 2
Download-URL: https://pypi.python.org/pypi/mlserve
Keywords: mlserve,serving,aiohttp
Platform: POSIX
Classifier: License :: OSI Approved :: Apache Software License
Classifier: Intended Audience :: Developers
Classifier: Programming Language :: Python :: 3
Classifier: Programming Language :: Python :: 3.6
Classifier: Programming Language :: Python :: 3.7
Classifier: Operating System :: POSIX
Classifier: Development Status :: 2 - Pre-Alpha
Classifier: Framework :: AsyncIO
